replay_client/__init__.py
replay_client/main.py
replay_client-0.4.1.dist-info/METADATA
replay_client-0.4.1.dist-info/WHEEL
replay_client-0.4.1.dist-info/entry_points.txt
replay_client-0.4.1.dist-info/RECORD
