Metadata-Version: 2.4
Name: replay-client
Version: 0.4.1
Summary: Dora Node client for replaying recorded data.
License: MIT
Author: Hennzau
Author-email: <dev@enzo-le-van.fr>
Requires-Python: >=3.9
Classifier: License :: OSI Approved :: MIT License
Classifier: Programming Language :: Python :: 3
Classifier: Programming Language :: Python :: 3.9
Classifier: Programming Language :: Python :: 3.10
Classifier: Programming Language :: Python :: 3.11
Classifier: Programming Language :: Python :: 3.12
Classifier: Programming Language :: Python :: 3.13
Classifier: Programming Language :: Python :: 3.14
Requires-Dist: dora-rs (==0.3.5)
Requires-Dist: pandas (>=2.2.2,<2.3.0)
